python_weather/__init__.py
python_weather/base.py
python_weather/client.py
python_weather/constants.py
python_weather/enums.py
python_weather/errors.py
python_weather/forecast.py
python_weather/version.py
python_weather-2.1.1.dist-info/licenses/LICENSE
python_weather-2.1.1.dist-info/METADATA
python_weather-2.1.1.dist-info/WHEEL
python_weather-2.1.1.dist-info/top_level.txt
python_weather-2.1.1.dist-info/RECORD
