Metadata-Version: 2.4
Name: python-weather
Version: 2.1.1
Summary: A free and asynchronous weather API wrapper made in Python, for Python.
Author: null8626
License: MIT
Project-URL: Documentation, https://python-weather.readthedocs.io/en/latest/
Project-URL: Repository, https://github.com/null8626/python-weather
Project-URL: Changelog, https://python-weather.readthedocs.io/en/latest/changelog.html
Project-URL: Donate via GitHub Sponsors, https://github.com/sponsors/null8626
Project-URL: Donate via Ko-fi, https://ko-fi.com/null8626
Keywords: weather,forecast,weather-forecast
Classifier: Development Status :: 5 - Production/Stable
Classifier: Intended Audience :: Education
Classifier: Intended Audience :: Developers
Classifier: Intended Audience :: Information Technology
Classifier: Natural Language :: English
Classifier: Operating System :: OS Independent
Classifier: Topic :: Education
Classifier: Topic :: Internet
Classifier: Topic :: Scientific/Engineering
Classifier: Topic :: Scientific/Engineering :: Astronomy
Classifier: Topic :: Software Development
Classifier: Topic :: Software Development :: Libraries
Classifier: Programming Language :: Python
Classifier: Programming Language :: Python :: 3
Classifier: Programming Language :: Python :: 3 :: Only
Classifier: Programming Language :: Python :: 3.10
Classifier: Programming Language :: Python :: 3.11
Classifier: Programming Language :: Python :: 3.12
Classifier: Programming Language :: Python :: 3.13
Classifier: Programming Language :: Python :: 3.14
Requires-Python: >=3.10
License-File: LICENSE
Requires-Dist: aiohttp>=3.13.2
Dynamic: license-file
